mateus_media/__init__.py
mateus_media/calcular_medias_mensais.py
mateus_media/cli.py
mateus_media/dados_de_média.xlsx
mateus_media/python
mateus_media-0.2.0.dist-info/entry_points.txt
mateus_media-0.2.0.dist-info/LICENSE.txt
mateus_media-0.2.0.dist-info/METADATA
mateus_media-0.2.0.dist-info/WHEEL
mateus_media-0.2.0.dist-info/RECORD
