Metadata-Version: 2.1
Name: mateus-media
Version: 0.2.0
Summary: calculo de medias radiação
License: Beerware
Author: Mateus
Author-email: mateus.kaiss@ufpr.br
Requires-Python: >=3.11,<4.0
Classifier: Development Status :: 5 - Production/Stable
Classifier: Environment :: Console
Classifier: License :: Other/Proprietary License
Classifier: Natural Language :: Portuguese (Brazilian)
Classifier: Programming Language :: Python :: 3
Classifier: Programming Language :: Python :: 3.11
Classifier: Programming Language :: Python :: 3.12
Classifier: Topic :: Education
Requires-Dist: rich (>=13.7.1,<14.0.0)
Requires-Dist: typer (>=0.12.3,<0.13.0)
Project-URL: Bug Tracker, https://github.com/matkiap/mateus-media/issues
Project-URL: Código, https://github.com/matkiap/mateus-media
Project-URL: Doação, https://apoia.se/livedepython
